docs/benchmark.ipynb
docs/changelog.md
docs/cli.md
docs/index.md
docs/Python API/benchmark.md
docs/Python API/index.md
docs/Python API/request_types.md
docs/Python API/response_types.md
filesender/__init__.py
filesender/api.py
filesender/auth.py
filesender/benchmark.py
filesender/config.py
filesender/download.py
filesender/log.py
filesender/main.py
filesender/request_types.py
filesender/response_types.py
venv/bin/rst2html.py
venv/bin/rst2html4.py
venv/bin/rst2html5.py
venv/bin/rst2latex.py
venv/bin/rst2man.py
venv/bin/rst2odt.py
venv/bin/rst2odt_prepstyles.py
venv/bin/rst2pseudoxml.py
venv/bin/rst2s5.py
venv/bin/rst2xetex.py
venv/bin/rst2xml.py
venv/bin/rstpep2html.py
filesender_client-2.1.1.dist-info/LICENSE
filesender_client-2.1.1.dist-info/METADATA
filesender_client-2.1.1.dist-info/WHEEL
filesender_client-2.1.1.dist-info/entry_points.txt
filesender_client-2.1.1.dist-info/top_level.txt
filesender_client-2.1.1.dist-info/RECORD
